odoo/addons/stock_card_report_value/README.rst
odoo/addons/stock_card_report_value/__init__.py
odoo/addons/stock_card_report_value/__manifest__.py
odoo/addons/stock_card_report_value/reports/__init__.py
odoo/addons/stock_card_report_value/reports/stock_card_report.py
odoo/addons/stock_card_report_value/reports/stock_card_report.xml
odoo/addons/stock_card_report_value/reports/stock_card_report_xlsx.py
odoo/addons/stock_card_report_value/static/description/icon.png
odoo14_addon_stock_card_report_value-14.0.1.0.1.dist-info/METADATA
odoo14_addon_stock_card_report_value-14.0.1.0.1.dist-info/WHEEL
odoo14_addon_stock_card_report_value-14.0.1.0.1.dist-info/top_level.txt
odoo14_addon_stock_card_report_value-14.0.1.0.1.dist-info/RECORD
